pg_podcast_toolkit/__init__.py
pg_podcast_toolkit/item.py
pg_podcast_toolkit/media_resource.py
pg_podcast_toolkit/podcast.py
pg_podcast_toolkit/podcast_ipfs_tools.py
pg_podcast_toolkit/podcast_tools.py
pg_podcast_toolkit-0.2.1.dist-info/METADATA
pg_podcast_toolkit-0.2.1.dist-info/WHEEL
pg_podcast_toolkit-0.2.1.dist-info/licenses/LICENSE
pg_podcast_toolkit-0.2.1.dist-info/RECORD
